brplotviz/__init__.py
brplotviz/plot/__init__.py
brplotviz/plot/styleselect.py
brplotviz/table/__init__.py
brplotviz/table/rules.py
brplotviz/table/styles.py
brplotviz-0.3.2.dist-info/LICENSE
brplotviz-0.3.2.dist-info/METADATA
brplotviz-0.3.2.dist-info/WHEEL
brplotviz-0.3.2.dist-info/top_level.txt
brplotviz-0.3.2.dist-info/RECORD
