Metadata-Version: 2.1
Name: brplotviz
Version: 0.3.2
Summary: Utilities for nicely formatted tables and plots
Author-email: Bertram Richter <bertram.richter@tu-dresden.de>
Maintainer-email: Bertram Richter <bertram.richter@tu-dresden.de>
License: GNU GENERAL PUBLIC LICENSE
Project-URL: Homepage, https://github.com/bertramrichter/brplotviz
Project-URL: Bug Reports, https://github.com/bertramrichter/brplotviz/issues
Project-URL: Source, https://github.com/bertramrichter/brplotviz
Keywords: plot,table,pretty-print
Classifier: Framework :: Matplotlib
Classifier: License :: OSI Approved :: GNU General Public License v3 (GPLv3)
Classifier: Programming Language :: Python :: 3
Classifier: Programming Language :: Python :: 3.7
Classifier: Programming Language :: Python :: 3.8
Classifier: Programming Language :: Python :: 3.9
Classifier: Programming Language :: Python :: 3.10
Classifier: Programming Language :: Python :: 3.11
Classifier: Programming Language :: Python :: 3.12
Classifier: Programming Language :: Python :: 3 :: Only
Requires-Python: >=3.7
License-File: LICENSE
Requires-Dist: matplotlib>=3.5.0
Requires-Dist: numpy
